{"path":"Knisja%20tal-Vittorja","deepCounters":{"total":5,"images":5,"files":5},"counters":{"total":5,"images":5,"files":5},"thumb":{"path":"Knisja%20tal-Vittorja.jpg","width":337,"height":450},"album":{"description":"Valetta, Gozo, Malta. Winter 2023.\n\nBotanical, Gozo, Valetta, Museums, Malta, City, Fungi, Flora, Ocean, Architecture.","title":"Malta 2023: Boriss Melikjan Expeditions Collection."},"objects":[{"path":"IMG_4832.jpeg","image":{"path":"slides\/IMG_4832.jpeg","width":810,"height":1080},"thumb":{"path":"thumbs\/IMG_4832.jpeg","width":270,"height":360},"fileSize":3052398,"name":"IMG_4832.jpeg","fileDate":"2023-12-28T18:38:05.803Z","category":"image","camera":{"aperture":1.6,"exposureTime":"1\/362s","originalDate":"2023-12-18T11:06:57.0Z","cameraModel":"iPhone 12 Pro Max","location":{"altitude":"52.56 metres","latitude":"35° 53' 47.15\"","lat":35.89643,"long":14.511386,"longitude":"14° 30' 40.99\""},"focalLength35mm":"46mm","resolution":"4032 x 3024","cameraMake":"Apple","isoEquivalent":32,"flash":"Flash did not fire","focalLength":"5mm"}},{"path":"IMG_4833.jpeg","image":{"path":"slides\/IMG_4833.jpeg","width":810,"height":1080},"thumb":{"path":"thumbs\/IMG_4833.jpeg","width":270,"height":360},"fileSize":1727900,"name":"IMG_4833.jpeg","fileDate":"2023-12-28T18:38:08.601Z","category":"image","camera":{"aperture":1.6,"exposureTime":"1\/1439s","originalDate":"2023-12-18T11:08:11.0Z","cameraModel":"iPhone 12 Pro Max","location":{"altitude":"41.25 metres","latitude":"35° 53' 45.33\"","lat":35.895924,"long":14.511072,"longitude":"14° 30' 39.86\""},"focalLength35mm":"62mm","resolution":"4032 x 3024","cameraMake":"Apple","isoEquivalent":32,"flash":"Flash did not fire","focalLength":"5mm"}},{"path":"IMG_4834.jpeg","image":{"path":"slides\/IMG_4834.jpeg","width":810,"height":1080},"thumb":{"path":"thumbs\/IMG_4834.jpeg","width":270,"height":360},"fileSize":1758313,"name":"IMG_4834.jpeg","fileDate":"2023-12-28T18:38:02.302Z","category":"image","camera":{"aperture":1.6,"exposureTime":"1\/1439s","originalDate":"2023-12-18T11:08:11.0Z","cameraModel":"iPhone 12 Pro Max","location":{"altitude":"45.82 metres","latitude":"35° 53' 45.37\"","lat":35.895935,"long":14.511075,"longitude":"14° 30' 39.87\""},"focalLength35mm":"62mm","resolution":"4032 x 3024","cameraMake":"Apple","isoEquivalent":32,"flash":"Flash did not fire","focalLength":"5mm"}},{"path":"IMG_4835.jpeg","image":{"path":"slides\/IMG_4835.jpeg","width":810,"height":1080},"thumb":{"path":"thumbs\/IMG_4835.jpeg","width":270,"height":360},"fileSize":3894531,"name":"IMG_4835.jpeg","fileDate":"2023-12-28T18:38:02.391Z","category":"image","camera":{"aperture":2.2,"exposureTime":"1\/165s","originalDate":"2023-12-18T11:08:27.0Z","cameraModel":"iPhone 12 Pro Max","location":{"altitude":"55.77 metres","latitude":"35° 53' 45.75\"","lat":35.89604,"long":14.511014,"longitude":"14° 30' 39.65\""},"focalLength35mm":"80mm","resolution":"4032 x 3024","cameraMake":"Apple","isoEquivalent":20,"flash":"Flash did not fire","focalLength":"8mm"}},{"path":"IMG_4836.jpeg","image":{"path":"slides\/IMG_4836.jpeg","width":810,"height":1080},"thumb":{"path":"thumbs\/IMG_4836.jpeg","width":270,"height":360},"fileSize":4068713,"name":"IMG_4836.jpeg","fileDate":"2023-12-28T18:37:56.593Z","category":"image","camera":{"aperture":2.2,"exposureTime":"1\/156s","originalDate":"2023-12-18T11:08:28.0Z","cameraModel":"iPhone 12 Pro Max","location":{"altitude":"55.77 metres","latitude":"35° 53' 45.75\"","lat":35.89604,"long":14.511014,"longitude":"14° 30' 39.65\""},"focalLength35mm":"80mm","resolution":"4032 x 3024","cameraMake":"Apple","isoEquivalent":20,"flash":"Flash did not fire","focalLength":"8mm"}}],"name":"Knisja tal-Vittorja","theme":{"path":"ja-theme.jpg","width":1920,"height":800},"fileDate":"2023-12-28T22:45:37.288Z"}